panimg/__init__.py
panimg/cli.py
panimg/exceptions.py
panimg/models.py
panimg/panimg.py
panimg/settings.py
panimg/types.py
panimg/contrib/__init__.py
panimg/contrib/oct_converter/__init__.py
panimg/contrib/oct_converter/image_types/__init__.py
panimg/contrib/oct_converter/image_types/fundus.py
panimg/contrib/oct_converter/image_types/oct.py
panimg/contrib/oct_converter/readers/__init__.py
panimg/contrib/oct_converter/readers/e2e.py
panimg/contrib/oct_converter/readers/fda.py
panimg/contrib/oct_converter/readers/fds.py
panimg/contrib/wsi_dcm_to_tiff/__init__.py
panimg/contrib/wsi_dcm_to_tiff/dcm_to_tiff.py
panimg/contrib/wsi_isyntax_to_tiff/__init__.py
panimg/contrib/wsi_isyntax_to_tiff/isyntax_to_tiff.py
panimg/image_builders/__init__.py
panimg/image_builders/dicom.py
panimg/image_builders/fallback.py
panimg/image_builders/metaio_mhd_mha.py
panimg/image_builders/metaio_nifti.py
panimg/image_builders/metaio_nrrd.py
panimg/image_builders/metaio_utils.py
panimg/image_builders/oct.py
panimg/image_builders/tiff.py
panimg/post_processors/__init__.py
panimg/post_processors/tiff_to_dzi.py
panimg-0.16.1.dist-info/licenses/LICENSE
panimg-0.16.1.dist-info/METADATA
panimg-0.16.1.dist-info/WHEEL
panimg-0.16.1.dist-info/entry_points.txt
panimg-0.16.1.dist-info/top_level.txt
panimg-0.16.1.dist-info/RECORD
