Metadata-Version: 2.4
Name: panimg
Version: 0.16.1
Summary: Conversion of medical images to MHA and TIFF.
Author: James Meakin
License: Apache-2.0
Project-URL: repository, https://github.com/DIAGNijmegen/rse-panimg
Classifier: Development Status :: 3 - Alpha
Classifier: Intended Audience :: Developers
Classifier: Intended Audience :: Healthcare Industry
Classifier: Operating System :: POSIX
Requires-Python: <4.0,>=3.10
License-File: LICENSE
Requires-Dist: pydantic>=2
Requires-Dist: numpy>=1.22
Requires-Dist: SimpleITK!=2.1.1.1,>=2.0
Requires-Dist: pydicom>=2.2
Requires-Dist: Pillow
Requires-Dist: openslide-python
Requires-Dist: pyvips
Requires-Dist: tifffile
Requires-Dist: construct
Requires-Dist: click
Requires-Dist: pylibjpeg
Requires-Dist: pylibjpeg-libjpeg
Requires-Dist: pylibjpeg-openjpeg
Requires-Dist: wsidicom>=0.10.0
Requires-Dist: imagecodecs>=2023.3.16
Provides-Extra: isyntax
Requires-Dist: pyisyntax>=0.1.5; extra == "isyntax"
Dynamic: license-file
